{
  "request": [
    {
      "note1": "This perfectly thin cut just melts in your mouth.",
      "note2": "I had a really good day",
      "note3": "I went for a walk with my d",
      "id": 1
    },
    {
      "note1": "This perfectly thin cut just melts in your mouth.",
      "note2": "I had a really good day",
      "note3": "I went for a walk with my d",
      "id": 2
    },
    {
      "note1": "This perfectly thin cut just melts in your mouth.",
      "note2": "I had a really good day",
      "note3": "I went for a walk with my d",
      "id": 3
    },
    {
      "note1": "This perfectly thin cut just melts in your mouth.",
      "note2": "I had a really good day",
      "note3": "I went for a walk with my d",
      "id": 4
    },
    {
      "note1": "This perfectly thin cut just melts in your mouth.",
      "note2": "I had a really good day",
      "note3": "I went for a walk with my d",
      "id": 5
    }
  ]
}
